setup.py
pickle_converter/__init__.py
pickle_converter/main.py
pickle_converter.egg-info/PKG-INFO
pickle_converter.egg-info/SOURCES.txt
pickle_converter.egg-info/dependency_links.txt
pickle_converter.egg-info/entry_points.txt
pickle_converter.egg-info/not-zip-safe
pickle_converter.egg-info/top_level.txt