Metadata-Version: 1.0
Name: pickle-converter
Version: 0.1
Summary: Python pickle converter for data portability.
Home-page: http://packages.python.org/pickle_converter
Author: Mate Gabri
Author-email: mate@gabri.hu
License: BSD
Keywords: python pickle json converter
Platform: UNKNOWN
Classifier: Development Status :: 4 - Beta
Classifier: License :: OSI Approved :: BSD License
Classifier: Topic :: Utilities
